webpreview/__init__.py
webpreview/cli.py
webpreview/excepts.py
webpreview/helpers.py
webpreview/models.py
webpreview/parsers.py
webpreview/previews.py
webpreview/regex.py
webpreview/tests/__init__.py
webpreview/tests/test_fixtures.py
webpreview/tests/test_generic_preview.py
webpreview/tests/test_opengraph.py
webpreview/tests/test_preview_base.py
webpreview/tests/test_schema.py
webpreview/tests/test_twittercard.py
webpreview/tests/test_web_preview.py
webpreview/version.py
webpreview-1.7.2.dist-info/entry_points.txt
webpreview-1.7.2.dist-info/LICENSE.txt
webpreview-1.7.2.dist-info/WHEEL
webpreview-1.7.2.dist-info/METADATA
webpreview-1.7.2.dist-info/RECORD
